MANIFEST.in
README.rst
requirements.stable.txt
requirements.txt
setup.py
tasks.py
lino_vilma/__init__.py
lino_vilma/setup_info.py
lino_vilma.egg-info/PKG-INFO
lino_vilma.egg-info/SOURCES.txt
lino_vilma.egg-info/dependency_links.txt
lino_vilma.egg-info/not-zip-safe
lino_vilma.egg-info/requires.txt
lino_vilma.egg-info/top_level.txt
lino_vilma/lib/__init__.py
lino_vilma/lib/contacts/__init__.py
lino_vilma/lib/contacts/models.py
lino_vilma/lib/contacts/fixtures/__init__.py
lino_vilma/lib/contacts/fixtures/demo.py
lino_vilma/lib/vilma/__init__.py
lino_vilma/lib/vilma/help_texts.py
lino_vilma/lib/vilma/migrate.py
lino_vilma/lib/vilma/models.py
lino_vilma/lib/vilma/settings.py
lino_vilma/lib/vilma/user_types.py
lino_vilma/lib/vilma/workflows.py
lino_vilma/lib/vilma/fixtures/__init__.py
lino_vilma/lib/vilma/fixtures/linotickets.py
lino_vilma/lib/vilma/locale/de/LC_MESSAGES/django.mo
lino_vilma/lib/vilma/locale/de/LC_MESSAGES/django.po
lino_vilma/lib/vilma/locale/et/LC_MESSAGES/django.mo
lino_vilma/lib/vilma/locale/et/LC_MESSAGES/django.po
lino_vilma/lib/vilma/locale/fr/LC_MESSAGES/django.mo
lino_vilma/lib/vilma/locale/fr/LC_MESSAGES/django.po
tests/__init__.py