Metadata-Version: 1.1
Name: lino-vilma
Version: 20.1
Summary: A Lino application for managing village contacts
Home-page: http://vilma.lino-framework.org
Author: Luc Saffre
Author-email: luc@lino-framework.org
License: BSD-2-Clause
Platform: UNKNOWN
Classifier: Programming Language :: Python
Classifier: Programming Language :: Python :: 3
Classifier: Development Status :: 4 - Beta
Classifier: Environment :: Web Environment
Classifier: Framework :: Django
Classifier: Intended Audience :: Developers
Classifier: Intended Audience :: System Administrators
Classifier: Intended Audience :: Information Technology
Classifier: Intended Audience :: Customer Service
Classifier: License :: OSI Approved :: BSD License
Classifier: Operating System :: OS Independent
Classifier: Topic :: Software Development :: Bug Tracking
